pybumper/__init__.py
pybumper/bump_type.py
pybumper/git_helper.py
pybumper/main.py
pybumper/monorepo_helper.py
pybumper/version_bumper.py
pybumper/version_helper.py
pybumper-0.2.2.dist-info/METADATA
pybumper-0.2.2.dist-info/WHEEL
pybumper-0.2.2.dist-info/entry_points.txt
pybumper-0.2.2.dist-info/RECORD
