Metadata-Version: 2.4
Name: pybumper
Version: 0.2.2
Summary: Comprehensive version bumping for Python projects
Project-URL: repository, https://github.com/dannystewart/pybumper
Author-email: Danny Stewart <danny@stewart.cc>
Requires-Python: >=3.12
Requires-Dist: dsbase
